unifi_tracker/__init__.py
unifi_tracker/unifi_tracker.py
unifi_tracker-0.1.2.dist-info/LICENSE
unifi_tracker-0.1.2.dist-info/METADATA
unifi_tracker-0.1.2.dist-info/WHEEL
unifi_tracker-0.1.2.dist-info/top_level.txt
unifi_tracker-0.1.2.dist-info/RECORD
