Metadata-Version: 2.1
Name: unifi_tracker
Version: 0.1.2
Summary: Track the comings and goings of WiFi clients on multiple Unifi APs and generate a diff between scans.
Author-email: "Joel P." <joelp@live.com>
License: MIT License
Project-URL: Homepage, https://github.com/idatum/unifi_tracker
Project-URL: Issues, https://github.com/idatum/unifi_tracker/issues
Keywords: unifi,wifi,tracker,presence,mqtt
Classifier: Programming Language :: Python :: 3
Classifier: License :: OSI Approved :: MIT License
Classifier: Operating System :: OS Independent
Requires-Python: >=3.9
License-File: LICENSE
Requires-Dist: paramiko >=2.12
Provides-Extra: paho-mqtt
Requires-Dist: paho-mqtt >=2.0 ; extra == 'paho-mqtt'
